keneth/kernel_contracts/__init__.py
keneth/kernel_contracts/request_handler.py
keneth_kernel_contracts-0.2.0.dist-info/licenses/LICENSE
keneth_kernel_contracts-0.2.0.dist-info/METADATA
keneth_kernel_contracts-0.2.0.dist-info/WHEEL
keneth_kernel_contracts-0.2.0.dist-info/top_level.txt
keneth_kernel_contracts-0.2.0.dist-info/RECORD
