Metadata-Version: 2.4
Name: keneth-kernel-contracts
Version: 0.2.0
Summary: Minimal contracts for the Keneth Python web framework.
Author-email: Ismaël Lucas de Leyssac <geodgit@duck.com>
License:                                  Apache License
Project-URL: Homepage, https://github.com/keneth-framework/kernel-contracts
Requires-Python: >=3.12
License-File: LICENSE
Requires-Dist: starlette>=0.45.0
Dynamic: license-file
